GraphesComplexes/Fonction.py
GraphesComplexes/Graphe.py
GraphesComplexes/__init__.py
GraphesComplexes/asup.py
GraphesComplexes/fonctions.py
GraphesComplexes/outils.py
graphescomplexes-0.1.2.dist-info/licenses/LICENSE
graphescomplexes-0.1.2.dist-info/METADATA
graphescomplexes-0.1.2.dist-info/WHEEL
graphescomplexes-0.1.2.dist-info/top_level.txt
graphescomplexes-0.1.2.dist-info/RECORD
