Metadata-Version: 2.4
Name: GraphesComplexes
Version: 0.1.2
Summary: Une bibliothèque simple pour visualiser les fonctions complexes
Author: Emmanuel Lafont
License-File: LICENSE
Requires-Dist: numpy
Requires-Dist: matplotlib
Dynamic: author
Dynamic: license-file
Dynamic: requires-dist
Dynamic: summary
